cardapio_unicamp/__init__.py
cardapio_unicamp/main.py
cardapio_unicamp-1.2.2.dist-info/LICENSE
cardapio_unicamp-1.2.2.dist-info/METADATA
cardapio_unicamp-1.2.2.dist-info/WHEEL
cardapio_unicamp-1.2.2.dist-info/entry_points.txt
cardapio_unicamp-1.2.2.dist-info/top_level.txt
cardapio_unicamp-1.2.2.dist-info/RECORD
