Metadata-Version: 2.1
Name: cardapio-unicamp
Version: 1.2.2
Summary: A menu fetcher for Unicamp's restaurant
Home-page: https://gitlab.com/nfraprado/cardapio-unicamp
Author: Nícolas F. R. A. Prado
Author-email: nfraprado@protonmail.com
License: UNKNOWN
Platform: UNKNOWN
Classifier: Programming Language :: Python :: 3
Classifier: License :: OSI Approved :: GNU General Public License v3 (GPLv3)
Classifier: Operating System :: OS Independent
Requires-Python: >=3
Requires-Dist: beautifulsoup4
Requires-Dist: requests
